raydar/__init__.py
raydar/dashboard/__init__.py
raydar/dashboard/demo.py
raydar/dashboard/server.py
raydar/dashboard/static/index.css
raydar/dashboard/static/index.html
raydar/dashboard/static/index.js
raydar/dashboard/static/layouts/default.json
raydar/task_tracker/__init__.py
raydar/task_tracker/schema.py
raydar/task_tracker/task_tracker.py
raydar/tests/__init__.py
raydar/tests/conftest.py
raydar/tests/test_task_tracker.py
raydar-0.2.4.dist-info/METADATA
raydar-0.2.4.dist-info/WHEEL
raydar-0.2.4.dist-info/licenses/LICENSE
raydar-0.2.4.dist-info/RECORD
