Metadata-Version: 2.3
Name: raydar
Version: 0.2.4
Summary: A perspective powered, user editable ray dashboard via ray serve
Project-URL: Repository, https://github.com/point72/raydar
Project-URL: Homepage, https://github.com/point72/raydar
Author-email: Point72 <OpenSource@Point72.com>
License:                                  Apache License
License-File: LICENSE
Keywords: cluster,cluster visualization,dashboard,data visualization,dataviz,perspective,ray
Classifier: Development Status :: 4 - Beta
Classifier: Framework :: Jupyter
Classifier: Framework :: Jupyter :: JupyterLab
Classifier: License :: OSI Approved :: Apache Software License
Classifier: Programming Language :: Python
Classifier: Programming Language :: Python :: 3
Classifier: Programming Language :: Python :: 3.8
Classifier: Programming Language :: Python :: 3.9
Classifier: Programming Language :: Python :: 3.10
Classifier: Programming Language :: Python :: 3.11
Classifier: Programming Language :: Python :: 3.12
Requires-Python: >=3.8
Requires-Dist: coolname
Requires-Dist: fastapi
Requires-Dist: packaging
Requires-Dist: perspective-python<3,>=2
Requires-Dist: polars
Requires-Dist: pyarrow
Requires-Dist: pydantic
Requires-Dist: ray[serve]>=2.8
Provides-Extra: develop
Requires-Dist: build; extra == 'develop'
Requires-Dist: bump-my-version; extra == 'develop'
Requires-Dist: check-manifest; extra == 'develop'
Requires-Dist: hatch-jupyter-builder; extra == 'develop'
Requires-Dist: hatchling; extra == 'develop'
Requires-Dist: pytest; extra == 'develop'
Requires-Dist: pytest-asyncio; extra == 'develop'
Requires-Dist: pytest-cov; extra == 'develop'
Requires-Dist: pytest-sugar; extra == 'develop'
Requires-Dist: ruff<0.7,>=0.5.0; extra == 'develop'
Requires-Dist: toml; extra == 'develop'
Requires-Dist: twine; extra == 'develop'
Requires-Dist: wheel; extra == 'develop'
Provides-Extra: test
Requires-Dist: pytest; extra == 'test'
Requires-Dist: pytest-asyncio; extra == 'test'
Requires-Dist: pytest-cov; extra == 'test'
Requires-Dist: pytest-sugar; extra == 'test'
